uitestrunner_syberos/Connection.py
uitestrunner_syberos/DataStruct.py
uitestrunner_syberos/Device.py
uitestrunner_syberos/Events.py
uitestrunner_syberos/Item.py
uitestrunner_syberos/TextItemFromOcr.py
uitestrunner_syberos/Watcher.py
uitestrunner_syberos/__init__.py
uitestrunner_syberos/__main__.py
uitestrunner_syberos/data/darwin_x86_64_phantomjs
uitestrunner_syberos/data/libsimulation-rendering-arm64.dylib
uitestrunner_syberos/data/libsimulation-rendering.dll
uitestrunner_syberos/data/libsimulation-rendering.dylib
uitestrunner_syberos/data/libsimulation-rendering.so
uitestrunner_syberos/data/linux_x86_64_phantomjs
uitestrunner_syberos/data/win32_x86_64_phantomjs.exe
uitestrunner_syberos/selenium_phantomjs/__init__.py
uitestrunner_syberos/selenium_phantomjs/webdriver/__init__.py
uitestrunner_syberos/selenium_phantomjs/webdriver/common/__init__.py
uitestrunner_syberos/selenium_phantomjs/webdriver/common/service.py
uitestrunner_syberos/selenium_phantomjs/webdriver/common/utils.py
uitestrunner_syberos/selenium_phantomjs/webdriver/remote/__init__.py
uitestrunner_syberos/selenium_phantomjs/webdriver/remote/command.py
uitestrunner_syberos/selenium_phantomjs/webdriver/remote/remote_connection.py
uitestrunner_syberos/selenium_phantomjs/webdriver/remote/utils.py
uitestrunner_syberos/selenium_phantomjs/webdriver/remote/webdriver.py
uitestrunner_syberos-2.18.4.dist-info/LICENSE
uitestrunner_syberos-2.18.4.dist-info/METADATA
uitestrunner_syberos-2.18.4.dist-info/WHEEL
uitestrunner_syberos-2.18.4.dist-info/top_level.txt
uitestrunner_syberos-2.18.4.dist-info/RECORD
