Metadata-Version: 2.1
Name: uitestrunner_syberos
Version: 2.18.4
Summary: A ui automated testing tool for SyberOS
Home-page: https://www.syberos.com/
Author: Jinzhe Wang
Author-email: wangjinzhe@syberos.com
Project-URL: Source, https://github.com/jinzhe0094/uitestrunner_syberos
Project-URL: Api Doc, https://doc.jinzhe.wang/uts/
Classifier: Programming Language :: Python :: 3
Classifier: License :: OSI Approved :: GNU General Public License v3 (GPLv3)
Classifier: Operating System :: OS Independent
Requires-Python: >=3.6, <=3.9
License-File: LICENSE
Requires-Dist: sseclient
Requires-Dist: paramiko
Requires-Dist: requests
Requires-Dist: PyNaCl
Requires-Dist: scp
Requires-Dist: lxml
Requires-Dist: urllib3<=1.26.18
Requires-Dist: opencv-python
Requires-Dist: numpy
Requires-Dist: psutil
Requires-Dist: sympy
Requires-Dist: scikit-build
Requires-Dist: Pillow
Requires-Dist: easyocr
Requires-Dist: torch
Requires-Dist: torchvision
Requires-Dist: ocrLangModel4uts
Requires-Dist: ocrCraftModel4uts
